{"timestamp": "2026-05-12 16:05", "price": 0.9718, "price_change_pct": -5.696, "volume_24h": 14.36, "oi_usdt": 31.31, "oi_coin": 32218867.5, "funding_rate": 0.005, "sm_total_traders": 489, "sm_long_traders": 275, "sm_short_traders": 214, "sm_long_whales": 87, "sm_short_whales": 163, "sm_long_pos_usdt": 8.44, "sm_short_pos_usdt": 17.65, "sm_ls_ratio": 0.4784, "sm_long_avg_price": 1.9795, "sm_short_avg_price": 1.1088, "sm_long_profit_pct": 22.2, "sm_short_profit_pct": 93.5, "sm30_long_traders": 26, "sm30_short_traders": 45, "sm30_long_whales": 14, "sm30_short_whales": 31, "sm30_long_pos_usdt": 30.3, "sm30_short_pos_usdt": 40.9, "global_ls_ratio": 3.0984, "top_pos_ls_ratio": 2.4982, "onchain_holders": 11607, "onchain_top10_pct": 3.99, "onchain_kol_holders": 0, "onchain_sm_holders": 0, "onchain_liquidity": 0.2, "taker_buy_sell_ratio": 0.9758, "taker_buy_vol": 0.1, "taker_sell_vol": 0.11, "depth_bid_total_k": 8.0, "depth_ask_total_k": 9.7, "depth_bid_wall_price": 0.9717, "depth_bid_wall_qty": 756, "depth_ask_wall_price": 0.9746, "depth_ask_wall_qty": 1380, "depth_ratio": 0.82, "tape_large_count": 0, "tape_medium_count": 0, "tape_large_buy": 0, "tape_large_sell": 0, "tape_aggr_buy_k": 17.8, "tape_aggr_sell_k": 18.8, "btc_price": 80787.0, "btc_24h_pct": 0.14, "river_vs_btc": -5.84}